{
  "mainMenu": [
    {
      "id": "1",
      "description": "Главная",
      "route" : "/main",
      "icon": "bi bi-house"
    },
    {
      "id": "2",
      "description": "Настройка периодов",
      "route" : "/periods",
      "icon": "bi bi-clock"
    },
    {
      "id": "3",
      "description": "Ввод данных",
      "route" : "/data",
      "icon": "bi bi-clipboard-data"
    },
    {
      "id": "4",
      "description": "Карта гарантий",
      "route" : "/map",
      "icon": "bi bi-map"
    }]
}